adcp/ADCP_VERSION
adcp/__init__.py
adcp/__main__.py
adcp/adagents.py
adcp/client.py
adcp/config.py
adcp/exceptions.py
adcp/py.typed
adcp/simple.py
adcp/validation.py
adcp/webhooks.py
adcp/protocols/__init__.py
adcp/protocols/a2a.py
adcp/protocols/base.py
adcp/protocols/mcp.py
adcp/server/__init__.py
adcp/server/base.py
adcp/server/content_standards.py
adcp/server/governance.py
adcp/server/mcp_tools.py
adcp/server/proposal.py
adcp/server/sponsored_intelligence.py
adcp/testing/__init__.py
adcp/testing/test_helpers.py
adcp/types/__init__.py
adcp/types/_ergonomic.py
adcp/types/_generated.py
adcp/types/aliases.py
adcp/types/base.py
adcp/types/coercion.py
adcp/types/core.py
adcp/types/generated_poc/__init__.py
adcp/types/generated_poc/adagents.py
adcp/types/generated_poc/content_standards/__init__.py
adcp/types/generated_poc/content_standards/artifact.py
adcp/types/generated_poc/content_standards/artifact_webhook_payload.py
adcp/types/generated_poc/content_standards/calibrate_content_request.py
adcp/types/generated_poc/content_standards/calibrate_content_response.py
adcp/types/generated_poc/content_standards/content_standards.py
adcp/types/generated_poc/content_standards/create_content_standards_request.py
adcp/types/generated_poc/content_standards/create_content_standards_response.py
adcp/types/generated_poc/content_standards/get_content_standards_request.py
adcp/types/generated_poc/content_standards/get_content_standards_response.py
adcp/types/generated_poc/content_standards/get_media_buy_artifacts_request.py
adcp/types/generated_poc/content_standards/get_media_buy_artifacts_response.py
adcp/types/generated_poc/content_standards/list_content_standards_request.py
adcp/types/generated_poc/content_standards/list_content_standards_response.py
adcp/types/generated_poc/content_standards/update_content_standards_request.py
adcp/types/generated_poc/content_standards/update_content_standards_response.py
adcp-3.1.0.dist-info/licenses/LICENSE
adcp-3.1.0.dist-info/METADATA
adcp-3.1.0.dist-info/WHEEL
adcp-3.1.0.dist-info/entry_points.txt
adcp-3.1.0.dist-info/top_level.txt
adcp-3.1.0.dist-info/RECORD
