Metadata-Version: 2.4
Name: adcp
Version: 3.1.0
Summary: Official Python client for the Ad Context Protocol (AdCP)
Author-email: AdCP Community <maintainers@adcontextprotocol.org>
License: Apache-2.0
Project-URL: Homepage, https://github.com/adcontextprotocol/adcp-client-python
Project-URL: Documentation, https://docs.adcontextprotocol.org
Project-URL: Repository, https://github.com/adcontextprotocol/adcp-client-python
Project-URL: Issues, https://github.com/adcontextprotocol/adcp-client-python/issues
Keywords: adcp,mcp,a2a,protocol,advertising
Classifier: Development Status :: 3 - Alpha
Classifier: Intended Audience :: Developers
Classifier: License :: OSI Approved :: Apache Software License
Classifier: Programming Language :: Python :: 3
Classifier: Programming Language :: Python :: 3.10
Classifier: Programming Language :: Python :: 3.11
Classifier: Programming Language :: Python :: 3.12
Classifier: Programming Language :: Python :: 3.13
Classifier: Topic :: Software Development :: Libraries :: Python Modules
Requires-Python: >=3.10
License-File: LICENSE
Requires-Dist: httpx>=0.24.0
Requires-Dist: pydantic>=2.0.0
Requires-Dist: typing-extensions>=4.5.0
Requires-Dist: a2a-sdk>=0.3.0
Requires-Dist: mcp>=1.23.2
Requires-Dist: email-validator>=2.0.0
Provides-Extra: dev
Requires-Dist: pytest>=7.0.0; extra == "dev"
Requires-Dist: pytest-asyncio>=0.21.0; extra == "dev"
Requires-Dist: pytest-cov>=4.0.0; extra == "dev"
Requires-Dist: mypy>=1.0.0; extra == "dev"
Requires-Dist: black>=23.0.0; extra == "dev"
Requires-Dist: ruff>=0.1.0; extra == "dev"
Requires-Dist: datamodel-code-generator[http]>=0.35.0; extra == "dev"
Provides-Extra: docs
Requires-Dist: pdoc3>=0.10.0; extra == "docs"
Dynamic: license-file
